{
  "todos": [
    {
      "id": 3,
      "title": "New Title",
      "detail": "Odio delectus est s",
      "complete": true
    },
    {
      "title": "Inventore dolore inc",
      "detail": "Officia in iste labo",
      "complete": true,
      "id": 4
    },
    {
      "title": "Ipsa aut deleniti d",
      "detail": "In eum aut ut et cum",
      "complete": false,
      "id": 5
    },
    {
      "title": "Temporibus quo amet",
      "detail": "Eveniet eveniet ve",
      "complete": false,
      "id": 6
    }
  ]
}